iselenium/__init__.py
iselenium-0.0.1.dist-info/LICENSE
iselenium-0.0.1.dist-info/METADATA
iselenium-0.0.1.dist-info/WHEEL
iselenium-0.0.1.dist-info/top_level.txt
iselenium-0.0.1.dist-info/RECORD
