Metadata-Version: 2.1
Name: iselenium
Version: 0.0.1
Summary: 
